LICENSE
MANIFEST.in
README.rst
requirements-dev.txt
requirements.txt
setup.cfg
setup.py
pypuppetdbquery/__init__.py
pypuppetdbquery/ast.py
pypuppetdbquery/evaluator.py
pypuppetdbquery/lexer.py
pypuppetdbquery/parser.py
pypuppetdbquery/version.py
pypuppetdbquery.egg-info/PKG-INFO
pypuppetdbquery.egg-info/SOURCES.txt
pypuppetdbquery.egg-info/dependency_links.txt
pypuppetdbquery.egg-info/requires.txt
pypuppetdbquery.egg-info/top_level.txt
tests/test_frontend.py
tests/test_integration.py
tests/test_lexer.py
tests/test_parser.py