Metadata-Version: 1.0
Name: pypuppetdbquery
Version: 0.9.1
Summary: A port of Erik Dalén's PuppetDB Query language to Python
Home-page: https://github.com/bootc/pypuppetdbquery/
Author: Chris Boot
Author-email: bootc@bootc.net
License: Apache-2.0
Platform: UNKNOWN
